{
  "_ts": 0,
  "id": "dcc51da7-9ba0-4993-a9ea-bcfbffd58549",
  "name": "Anke Richter",
  "youTubeChannelId": "UCdMOxR0JRZgr8qmM72X78Jw",
  "episodes": [
    {
      "id": "68b09191-ea4a-452c-aadc-dc7e806ce0fc",
      "title": "Poia Alpha Branch Davidians Survivor",
      "description": "Branch Davidians survivor Poia Alpha shares her thoughts ahead of Decult 2024. At Decult 2024 a survivor story jam will bring together other cult survivors and give opportunity for connection through",
      "release": "2024-10-14T08:31:32Z",
      "duration": "00:01:24",
      "explicit": false,
      "youTubeId": "Gv3rHBWQPnU",
      "subjects": [
        "Branch Davidians"
      ],
      "urls": {
        "youtube": "https://www.youtube.com/watch?v=Gv3rHBWQPnU"
      }
    },
    {
      "id": "9a23a2ce-c88d-4cf4-a4d9-72655706870f",
      "title": "50,000 New Zealanders affected by cults",
      "description": "Decult director Anke Richter went on Breakfast (TVNZ) to talk about the lasting harmful impact of high-demand groups in New Zealand and why Decult is addressing this problem with a pioneering cult awareness conference on 19 \u2013 20 October 2024. Watch how presenter Daniel Faitaua can\u2019t get his head around the baffling fact that an estimated number of 50,000 Kiwis are or were in cultic groups.                                           \n \nMore info: decult.net",
      "release": "2024-10-01T06:02:48Z",
      "duration": "00:07:15",
      "explicit": false,
      "youTubeId": "pVuRajJzV8Y",
      "subjects": [
        "Cult Psychology",
        "Cult-Expert"
      ],
      "urls": {
        "youtube": "https://www.youtube.com/watch?v=pVuRajJzV8Y"
      }
    },
    {
      "id": "e940ab56-1178-4ce0-9997-e954d5a4a9c0",
      "title": "ANKE RICHTER VISITS OSHO\u2019S \u201CCASHRAM\u201D",
      "description": "International journalist Anke Richter, bestselling author of \u201CCult Trip: Inside the world of coercion \u0026 control\u201D, spoke to PALAVER host Shay Horay at the Lyttelton Arts Factory about her 2017 trip to Bhagwan/Rajneesh\u2019s former commune in Pune/India \u2013 a bizarre place she would not revisit, given what has since come to light about the infamous guru and the suffering of sannyasin children.\n \nRead her story: https://www.stuff.co.nz/entertainment/tv-radio/104522551/journalist-anke-richter-goes-inside-the-cult-of-netflixs-wild-wild-country\n \nMore about the author and \u201CCult Trip\u201D: www.ankerichter.net",
      "release": "2023-11-01T18:31:18Z",
      "duration": "00:16:43",
      "explicit": false,
      "youTubeId": "aJbs6UQyTAs",
      "subjects": [
        "Bhagwan Shree Rajneesh",
        "Cult-Expert"
      ],
      "urls": {
        "youtube": "https://www.youtube.com/watch?v=aJbs6UQyTAs"
      }
    }
  ]
}