{
  "id": "7408f1ac-49b4-49e9-b8f2-4bd6615d3225",
  "name": "Apollo The Original",
  "spotifyId": "4Ky0AKXxi2bjZY2lRhjFyG",
  "appleId": 1672658698,
  "youTubeChannelId": "UCqqUxisCbZ_Hjn3CZawp1eg",
  "episodes": [
    {
      "id": "e5ade7ba-afcb-4198-9d3f-e5ca3484b821",
      "title": "Mormon Church Exposed: The Whole Truth",
      "description": "She Was in Mormon Cult for 35\u002B Years and Now She Exposes It\n\n\uD83C\uDFC6 Subscribe to my channel: https://bit.ly/4926kPy\n\n\uD83C\uDF81 Become a member and support my work: https://bit.ly/4iK6DTx\n\n\uD83D\uDD70\uFE0F Time codes for your convenience:\n\n00:00:01 Intro\n00:01:46 Her grandparents helped establishing the Mormon church\n00:04:36 How the Mormon church was built\n00:08:54 John Dee was the first 007\n00:09:44 Angelic language and the Enochian magic\n00:12:11 Who was Joseph Smith really?\n00:28:21 Mary Magdalene had children from Jesus\n00:39:11 Mormons used to do rituals and dig up treasures?\n00:40:52 Where is Jesus in Mormon church?\n00:43:21 What is the bloodline of Joseph Smith\n00:45:56 Bush and Smith are relatives?\n00:54:47 Mormons will have their own planet\n01:00:07 What was so special about Joseph Smith?\n01:03:23 The Vatican and Mormon church\n01:07:14 Mormon Temples and Churches\n01:08:42 Mormons are Masons?\n01:15:30 Garment price\n01:21:00 Polygamy in Mormon Church\n01:23:51 Mormon prophets\n01:26:56 Mormons are only white? No blacks, hispanics and etc?\n01:35:55 How much do you have to give to Mormon church?\n01:37:20 Bill Gates\u0027 ties with Mormons\n01:47:20 New Mormon prophet\n01:42:30 Mormons baptize dead people\n01:46:16 Cult of the Black Sticks\n01:49:37 Howard Hughes a vampire?\n\nHeidi Luv has been in the Mormon (Latter Day Saints) church since she was born. It took her 35\u002B years to realize it\u0027s a cult and now Heidi shares her knowledge, experience and investigations bringing the truth about Mormon church.\nHeidi is a wife, a mother, a grandmother and a woman of God.\n\nFollow Heidi on social media:\n\uD83D\uDC49 https://www.youtube.com/@UCIPeDFNe8CUt0_8aIg9rPWQ \n\uD83D\uDC49 https://www.instagram.com/unfilteredrise_podcast\n\uD83D\uDC49 https://www.unfilteredpodcast.com/\n\nApollo The Original Podcast on audio platforms:\n\uD83D\uDC49 Apple Podcast: https://apple.co/4eM0xiy\n\uD83D\uDC49 Spotify: https://spoti.fi/4eHJH4f\n\n\u2705  Stay Connected With Me: \n\n\uD83D\uDC49 Instagram: https://www.instagram.com/apollo.the.original \n\uD83D\uDC49 Twitter(X): http://www.x.com/apollotheorigin\n\uD83D\uDC49 My Youtube Short Clips: https://www.youtube.com/@apollotheoriginalshorts\n \n==============================\n\n\u2705 Other Videos You Might Be Interested In Watching: \n\n\uD83D\uDC49 Bible Proves We Live in Satan\u0027s Little Season:\nhttps://youtu.be/OeUaOLqcuLg?si=RDZvZGId4LECFpUy\n\n\uD83D\uDC49 Real Life Giants \u0026 Nephilim:\nhttps://youtu.be/3I9f-6uJhWg?si=kZ9Dm08u_c2x8loN\n\n=============================\n\n\u2705  About Apollo The Original: \n\nThis podcast dives deep into uncovering hidden truths and controversial stories in politics, religion, and society. With a focus on exposing corruption within institutions like the church, state, and schools, it explores topics such as money laundering, sex trafficking, and the exploitation of children, aiming to shine a light on the darker sides of power.\n\n=====================\n\n#mormons  #josephsmith #latterdaysaints  \n\nDisclaimer: We do not accept any liability for any loss or damage which is incurred from you acting or not acting as a result of reading any of our publications. You acknowledge that you use the information we provide at your own risk. Do your own research.  \n\nCopyright Disclaimer: Under Section 107 of the Copyright Act 1976, allowance is made for \u0022fair use\u0022 for purposes such as criticism, comment, news reporting, teaching, scholarship and research. Fair use is a use permitted by copyright statute that might otherwise be infringing. Non-profit, educational or personal use tips the balance in favor of fair use\n\n\u00A9 Apollo The Original",
      "release": "2026-02-25T02:00:07Z",
      "duration": "02:04:29",
      "explicit": false,
      "spotifyId": "6ii8Gbq1MoVPlXcSlYxYXd",
      "appleId": 1000751278793,
      "youTubeId": "GBU5JJ3i4jw",
      "subjects": [
        "The Church Of Jesus Christ Of Latter-Day Saints"
      ],
      "urls": {
        "spotify": "https://open.spotify.com/episode/6ii8Gbq1MoVPlXcSlYxYXd",
        "apple": "https://podcasts.apple.com/podcast/mormon-church-cult-exposed/id1672658698?i=1000751278793",
        "youtube": "https://www.youtube.com/watch?v=GBU5JJ3i4jw"
      }
    }
  ]
}