{
  "id": "79f5ba4a-e46d-4696-98de-22ca102028a8",
  "name": "morbidforfun",
  "youTubeChannelId": "UCDRWjlrtmaZf9L1fuU_8niA",
  "episodes": [
    {
      "id": "72ee955a-a879-4579-bf05-f66fa444100f",
      "title": "I Found Jeffrey Epstein\u0027s Secret YouTube Channel",
      "description": "A few days ago, buried inside reorganized federal records, we found what appears to be Jeffrey Epstein\u2019s YouTube channel. Created in 2008. Two subscribers. No uploads. Deleted within days of being discovered. But through the Jmail archive, the footprint it left behind still exists.\n\nSocials\nInstagram: https://www.Instagram.com/morbidforfun \nTikTok: https://www.tiktok.com/@morbidforfun\nTwitter: https://twitter.com/morbidforfun\n\nThank you @farrellmcguire for appearing in my video!\n\nThis video is created for educational, artistic, and documentary purposes only. It is not intended to sensationalize or glorify crime in any way. All information presented is based on publicly available sources and is shared to provide historical, cultural, and educational context. Viewer discretion is advised.\n\nMusic used: https://youtu.be/I78HUBTIVyM?si=6OMS0n2nnOuCnBJr\nThank you  @Mustlord_Guitar_Ambient  for allowing me to use your music!\n\nThanks for watching!",
      "release": "2026-02-21T20:00:00Z",
      "duration": "00:27:57",
      "explicit": false,
      "youTubeId": "Lkvzt7PtGGU",
      "subjects": [
        "Human Trafficking",
        "_America"
      ],
      "urls": {
        "youtube": "https://www.youtube.com/watch?v=Lkvzt7PtGGU"
      }
    },
    {
      "id": "76394a72-2da1-4907-83da-b1506916269d",
      "title": "Americas Most Dangerous Cults",
      "description": "Over the past years there has been a lot of cults in America that caused havoc. So in todays video we talk about the most dangerous cults in America.\n\nSome of the cults we talk about are the infamous Heavens gate cult which lead to a lot of tragic deaths, The peoples temple which is a cult ran by Jim Johns who is responsible for the Jonestown massacre, The Manson family which is a cult ran by the infamous Charles Manson, as well as many other cults that you probably haven\u0027t heard of.\n\nSocials\nInstagram: https://www.Instagram.com/morbidforfun \nTikTok: https://www.tiktok.com/@morbidforfun\nTwitter: https://twitter.com/morbidforfun\n\nThis video is for educational, artistic, and documentary purposes.\n\nHeavens Gate 0:00\nThe Manson Family 3:30\nThe Peoples Temple 6:43\nBranch Davidian\u0027s 10:22\nNXIVM 14:30\nChurch of the Lambs of God 18:41\nFundamentalist Church of Jesus Christ of Latter-day Saints 20:56\n\nComment \u0022nah that\u0027s brazy\u0022 so Internet Anarchist will let me see my family",
      "release": "2024-11-30T20:00:24Z",
      "duration": "00:24:53",
      "explicit": false,
      "youTubeId": "xv8UEaFRWj4",
      "subjects": [
        "Heaven\u0027s Gate",
        "Manson Family",
        "Peoples Temple",
        "Branch Davidians",
        "FLDS Church",
        "NXIVM",
        "The Church Of Jesus Christ Of Latter-Day Saints",
        "_America"
      ],
      "urls": {
        "youtube": "https://www.youtube.com/watch?v=xv8UEaFRWj4"
      }
    }
  ]
}