{
  "_ts": 0,
  "id": "1feb9e03-8e40-4383-897a-acf3c8e47f1b",
  "name": "One News PH",
  "youTubeChannelId": "UCzEAC4xGrhpShopTYgBhGJA",
  "episodes": [
    {
      "id": "2d4c07dd-e2e1-4fa8-a40e-d420218d1643",
      "title": "29 KOJC members face charges as 60 cops injured in Quiboloy hunt",
      "description": "#OneNewsNow | At least 29 Kingdom of Jesus Christ (KOJC) members face charges after 60 police officers were injured during the execution of an arrest warrant for pastor Apollo Quiboloy. | via #MOJO Evan Tarinque\n\nSubscribe to One News PH here:\nhttps://www.youtube.com/c/OneNewsPH\n\nFind One News PH here: https://onenews.ph\nFacebook: https://www.facebook.com/ONENewsPH/\nTwitter: https://twitter.com/onenewsph\nViber: https://bit.ly/36uQLSo\nTelegram: https://t.me/onenewsph",
      "release": "2024-08-30T03:19:43Z",
      "duration": "00:02:46",
      "explicit": false,
      "youTubeId": "EZUj1YvttKM",
      "subjects": [
        "Apollo Quiboloy"
      ],
      "urls": {
        "youtube": "https://www.youtube.com/watch?v=EZUj1YvttKM"
      }
    },
    {
      "id": "67af0280-f92b-4022-ae81-c613acc5364f",
      "title": "PNP detects possible underground bunker in KOJC Compound, intensifies search for Apollo Quiboloy",
      "description": "#TheBigStory | PNP Spokesperson Col. Jean Fajardo said that the PNP believes Apollo Quiboloy and other accused individuals are inside the KOJC compound, with ground-penetrating radar detecting heartbeats 20-30 meters underground, leading to a focused search for the bunker\u2019s entrance.\n\nSubscribe to One News PH here:\nhttps://www.youtube.com/c/OneNewsPH\n\nFind One News PH here: https://onenews.ph\nFacebook: https://www.facebook.com/ONENewsPH/\nTwitter: https://twitter.com/onenewsph\nViber: https://bit.ly/36uQLSo\nTelegram: https://t.me/onenewsph",
      "release": "2024-08-26T23:21:04Z",
      "duration": "00:03:32",
      "explicit": false,
      "youTubeId": "TP_PRlDNa3Y",
      "subjects": [
        "Apollo Quiboloy"
      ],
      "urls": {
        "youtube": "https://www.youtube.com/watch?v=TP_PRlDNa3Y"
      }
    }
  ]
}