{
  "id": "aa0a0707-e293-4c1a-ae45-95abef16da68",
  "name": "Prime Video",
  "youTubeChannelId": "UCQJWtTnAHhEG5w4uN0udnUQ",
  "episodes": [
    {
      "id": "49158dcb-25f3-4b6f-85a9-0f1b75ca4963",
      "title": "Shiny Happy People: A Teenage Holy War, Season 2 - Official Trailer | Prime Video",
      "description": "Season 2 coming to Prime Video July 23, 2025.\n\nTeen Mania captivated a generation of fervent evangelical Millennial kids with adrenaline-fueled, ecstatic religious experiences through \u201CAcquire the Fire\u201D rallies. But beneath the glittering surface lurked sadistic boot camps, staged martyrdom drills, and fascism disguised as faith - transforming innocent teens into fanatical soldiers, with devastating consequences still unfolding today.\n\n\u00BB SUBSCRIBE: http://bit.ly/PrimeVideoSubscribe\n \nAbout Prime Video:\nWant to watch it now? We\u2019ve got it. This week\u2019s newest movies, last night\u2019s TV shows, classic favorites, and more are available to stream instantly, plus all your videos are stored in Your Video Library. Prime Video offers a variety of unique and captivating entertainment, including original series \u201CThe Boys,\u201D \u201CInvincible,\u201D \u201CHazbin Hotel,\u201D \u201CThe Summer I Turned Pretty,\u201D and more.\n \nGet More Prime Video: \nStream Now: http://bit.ly/WatchMorePrimeVideo\nInstagram: http://bit.ly/primevideoIG\nTikTok: https://bit.ly/PrimeVideoTikTok\nFacebook: http://bit.ly/PrimeVideoFB\nX: http://bit.ly/PrimeVideoTW\n \nShiny Happy People: A Teenage Holy War, Season 2 - Official Trailer | Prime Video\nhttps://youtu.be/fKfEilxYpbM\n \nPrime Video\nhttps://www.youtube.com/PrimeVideo\n\n#ShinyHappyPeople #OfficialTrailer #PrimeVideo",
      "release": "2025-07-08T16:00:01Z",
      "duration": "00:02:13",
      "explicit": false,
      "youTubeId": "fKfEilxYpbM",
      "subjects": [
        "Teen Mania Ministries"
      ],
      "urls": {
        "youtube": "https://www.youtube.com/watch?v=fKfEilxYpbM"
      }
    }
  ]
}