{
  "id": "e40dd368-94bb-43b0-bf04-ac75f30749f6",
  "name": "Rodd and Real",
  "youTubeChannelId": "UC4mTAsQ52B3X8eKu18VkesA",
  "episodes": [
    {
      "id": "32ec635c-9b81-4675-91c7-84d9b033ae1e",
      "title": "Real Stories from former cult members!! ",
      "release": "2026-06-05T20:55:22Z",
      "duration": "00:15:40",
      "explicit": false,
      "youTubeId": "1_mtVn7SBAg",
      "subjects": [
        "Remnant Fellowship"
      ],
      "urls": {
        "youtube": "https://www.youtube.com/watch?v=1_mtVn7SBAg"
      }
    },
    {
      "id": "2cfcc394-0a37-41e8-9970-1092f02e5efd",
      "title": "WHO IS THE NEW \u2018CULT\u2019 LEADER?!",
      "release": "2026-05-24T23:37:49Z",
      "duration": "00:23:46",
      "explicit": false,
      "youTubeId": "Et-pb1ul6JY",
      "subjects": [
        "Remnant Fellowship"
      ],
      "urls": {
        "youtube": "https://www.youtube.com/watch?v=Et-pb1ul6JY"
      }
    },
    {
      "id": "89bfad38-3391-414d-8439-f5b7ff5980c4",
      "title": "WHAT IS THIS CULT HIDING?!",
      "description": "Trigger warning. This episode contains disturbing details of the case that brought Remnant Fellowship into the limelight. \n\nThis is part 3 of my \u201Cexposing Remnant Fellowship\u201D series. \n#cult #remnantfellowship #investigate #crime #truecrime",
      "release": "2026-05-10T22:22:12Z",
      "duration": "00:20:36",
      "explicit": false,
      "youTubeId": "hFTcy7G0zeg",
      "subjects": [
        "Remnant Fellowship"
      ],
      "urls": {
        "youtube": "https://www.youtube.com/watch?v=hFTcy7G0zeg"
      }
    },
    {
      "id": "1cffe76d-13d7-4efd-a210-799540245784",
      "title": "\u201CMembers of Remnant Fellowship won\u2019t like that I am saying this.\u201D PART 2 - Cult Exposed",
      "description": "In this documentary style series, Michael Black - formerly known as Michael Shamblin - opens up about his experience with Remnant Followship Church. \n\nIn part 2, we talk about religious discrimination and the extreme control tactics that this cult uses to keep their members submissive. \n\nWhat\u2019s terrifying is that this cult still operates today!",
      "release": "2026-05-04T00:55:47Z",
      "duration": "00:28:53",
      "explicit": false,
      "youTubeId": "0yVTL8VWGWY",
      "subjects": [
        "Remnant Fellowship"
      ],
      "urls": {
        "youtube": "https://www.youtube.com/watch?v=0yVTL8VWGWY"
      }
    },
    {
      "id": "dbf2c3a9-28db-4910-a6ee-ac9b5e42ee92",
      "title": "Cult Leader\u2019s Son Breaks his Silence!! Part 1",
      "description": "Michael Black, formerly known as Michael Shamblin, recounts some of his experiences as a former member of Remnant Church. Gwen Shamblin, who amassed a worldwide following through her faith based eating teachings, has been the subject of multiple documentaries, court cases and intense scrutiny.\n\nThis is part 1 of a 3 part series, with her own son opening up in this intense interview. \n#cult #documentary #truecrime #gwenshamblin #remnantchurch",
      "release": "2026-04-25T16:45:00Z",
      "duration": "00:20:23",
      "explicit": false,
      "youTubeId": "VCU7oX1GmWQ",
      "subjects": [
        "Remnant Fellowship"
      ],
      "urls": {
        "youtube": "https://www.youtube.com/watch?v=VCU7oX1GmWQ"
      }
    }
  ]
}