{
  "_ts": 0,
  "id": "3c406e7e-8be0-4ac1-bb1f-f47fb2bd375f",
  "name": "Stories of our times",
  "spotifyId": "7vE5B7Wdq2iNZLYXLwar5I",
  "appleId": 1501716010,
  "episodes": [
    {
      "id": "8be16cb5-eba4-422c-b750-957dbd68dffa",
      "title": "Inside California\u0027s \u0027orgasm commune\u0027",
      "description": "OneTaste, the organisation behind the practice \u0027orgasmic meditation\u0027, was hailed as visionary at its peak. Since then, its leader, Nicole Daedone, has been arrested by the FBI on forced labour charges and her group has been branded a \u0027cult\u0027 \u2013 allegations they deny vehemently. But what is it? Sunday Times reporter Megan Agnew was invited to their California compound, The Land, to find out.This podcast was brought to you thanks to the support of readers of The Times and The Sunday Times. Subscribe today: thetimes.co.uk/storiesofourtimes.\u00A0Guest: Megan Agnew, News Features Writer, The Sunday Times.Host: Jane Mulkerrins.Clips: ABC7 News, YouTube/Rebecca Watson, Eros Platform @OneTaste, goop.Get in touch: storiesofourtimes@thetimes.co.ukFind out more about our bonus series for Times subscribers: \u0027Inside the newsroom Hosted on Acast. See acast.com/privacy for more information.",
      "release": "2024-01-29T00:01:02Z",
      "duration": "00:37:40.6100000",
      "explicit": false,
      "spotifyId": "74YaP5X400go3wJxKNsc01",
      "appleId": 1000643300852,
      "subjects": [
        "Onetaste"
      ],
      "urls": {
        "spotify": "https://open.spotify.com/episode/74YaP5X400go3wJxKNsc01",
        "apple": "https://podcasts.apple.com/podcast/inside-californias-orgasm-commune/id1501716010?i=1000643300852"
      }
    }
  ]
}