{
  "id": "2313c394-1510-4fa4-a14c-dd623acb4381",
  "name": "Tocsin",
  "youTubeChannelId": "UCLuLxfwPrxe4wUPkdYM_VDA",
  "episodes": [
    {
      "id": "7be047fd-15c0-41cb-bdcf-efb1bded2fdf",
      "title": "D\u00E9cors rituels et initiatiques : d\u00E9couvrez la maison de Jeffrey Epstein - M-G Draghi",
      "description": "Les derni\u00E8res actualit\u00E9s sur l\u2019affaire Epstein\n\uD83D\uDD37Marc Gabriel Draghi \nJuriste sp\u00E9cialis\u00E9 dans l\u0027histoire du Droit\nAuteur de \u201CLe Grand Reset en marche ! 2020 : An 1 du nouvel ordre mondial\u201D, Ka\u2019\u00E9ditions, et de \u2018La Grande narration\u201D, 2022, Ka\u0027\u00E9ditions et derni\u00E8rement de CBDC une monnaie pour asservir l\u2019humanit\u00E9 Ka\u0027\u00E9ditions \n\nPour nous soutenir : https://www.tocsin-media.fr/soutien \n\nwww.tocsin-media.fr\n\n#epsteinfiles #jeffreyepstein #zorroranch #billgates",
      "release": "2026-05-12T11:00:57Z",
      "duration": "00:43:26",
      "explicit": false,
      "youTubeId": "eTTOVgxIBYY",
      "subjects": [
        "Human Trafficking",
        "_America"
      ],
      "urls": {
        "youtube": "https://www.youtube.com/watch?v=eTTOVgxIBYY"
      }
    },
    {
      "id": "ae2b2b00-abef-4311-ab35-4fb584e637d8",
      "title": "Jack Lang perd les p\u00E9dales face \u00E0 un journaliste sur Epstein !",
      "description": "Les derni\u00E8res actualit\u00E9s sur l\u2019affaire Epstein \n\uD83D\uDD37Marc Gabriel Draghi\nJuriste sp\u00E9cialis\u00E9 dans l\u0027histoire du Droit\nAuteur de \u201CLe Grand Reset en marche ! 2020 : An 1 du nouvel ordre mondial\u201D, Ka\u2019\u00E9ditions, et de \u2018La Grande narration\u201D, 2022, Ka\u0027\u00E9ditions\n\nPour nous soutenir : https://www.tocsin-media.fr/soutien \n\nwww.tocsin-media.fr\n\n#epstein #JackLang #rothschild #tocsin",
      "release": "2026-04-21T10:00:18Z",
      "duration": "00:34:24",
      "explicit": false,
      "youTubeId": "DuxofKq2rqg",
      "subjects": [
        "Human Trafficking",
        "_America"
      ],
      "urls": {
        "youtube": "https://www.youtube.com/watch?v=DuxofKq2rqg"
      }
    }
  ]
}